sacking/__init__.py
sacking/draft.py
sacking/environment.py
sacking/fc_network.py
sacking/policy.py
sacking/q_network.py
sacking/radam.py
sacking/replay_buffer.py
sacking/trainer.discrete.py
sacking/trainer.gaussian.py
sacking/trainer.py
sacking/typing.py
sacking/version.py
sacking-0.0.1.dev0.dist-info/LICENSE
sacking-0.0.1.dev0.dist-info/METADATA
sacking-0.0.1.dev0.dist-info/WHEEL
sacking-0.0.1.dev0.dist-info/top_level.txt
sacking-0.0.1.dev0.dist-info/RECORD
